{
  "project_info": {
    "project_number": "670667124999",
    "firebase_url": "https://multiindo.firebaseio.com",
    "project_id": "multiindo",
    "storage_bucket": "multiindo.appspot.com"
  },
  "client": [
    {
      "client_info": {
        "mobilesdk_app_id": "1:670667124999:android:f8fffc95efdbab084815a2",
        "android_client_info": {
          "package_name": "com.cindodcindy.vieroshoesadmin"
        }
      },
      "oauth_client": [
        {
          "client_id": "670667124999-28tf8jrkrgabhpgt2so8dm9b1vl8fcrj.apps.googleusercontent.com",
          "client_type": 3
        }
      ],
      "api_key": [
        {
          "current_key": "AIzaSyBJAw4XSqmrY0Z-Dpumfe9IxDwiKi5-KAQ"
        }
      ],
      "services": {
        "appinvite_service": {
          "other_platform_oauth_client": [
            {
              "client_id": "670667124999-28tf8jrkrgabhpgt2so8dm9b1vl8fcrj.apps.googleusercontent.com",
              "client_type": 3
            }
          ]
        }
      }
    },
    {
      "client_info": {
        "mobilesdk_app_id": "1:670667124999:android:d2cd65e2e5138e974815a2",
        "android_client_info": {
          "package_name": "com.cindodcindy.vieroshoesadminnew"
        }
      },
      "oauth_client": [
        {
          "client_id": "670667124999-qhpqchkmdv32kndeave50on6i8h51l64.apps.googleusercontent.com",
          "client_type": 1,
          "android_info": {
            "package_name": "com.cindodcindy.vieroshoesadminnew",
            "certificate_hash": "9e04ea77444cda9315e5422714f31ca878d0ea9b"
          }
        },
        {
          "client_id": "670667124999-28tf8jrkrgabhpgt2so8dm9b1vl8fcrj.apps.googleusercontent.com",
          "client_type": 3
        }
      ],
      "api_key": [
        {
          "current_key": "AIzaSyBJAw4XSqmrY0Z-Dpumfe9IxDwiKi5-KAQ"
        }
      ],
      "services": {
        "appinvite_service": {
          "other_platform_oauth_client": [
            {
              "client_id": "670667124999-28tf8jrkrgabhpgt2so8dm9b1vl8fcrj.apps.googleusercontent.com",
              "client_type": 3
            }
          ]
        }
      }
    },
    {
      "client_info": {
        "mobilesdk_app_id": "1:670667124999:android:4194b190e22611ac4815a2",
        "android_client_info": {
          "package_name": "com.cindodcindy.vieroshoesnew"
        }
      },
      "oauth_client": [
        {
          "client_id": "670667124999-mf86mkulon6kj9p0daiqohmrrecjm6tn.apps.googleusercontent.com",
          "client_type": 1,
          "android_info": {
            "package_name": "com.cindodcindy.vieroshoesnew",
            "certificate_hash": "9e04ea77444cda9315e5422714f31ca878d0ea9b"
          }
        },
        {
          "client_id": "670667124999-28tf8jrkrgabhpgt2so8dm9b1vl8fcrj.apps.googleusercontent.com",
          "client_type": 3
        }
      ],
      "api_key": [
        {
          "current_key": "AIzaSyBJAw4XSqmrY0Z-Dpumfe9IxDwiKi5-KAQ"
        }
      ],
      "services": {
        "appinvite_service": {
          "other_platform_oauth_client": [
            {
              "client_id": "670667124999-28tf8jrkrgabhpgt2so8dm9b1vl8fcrj.apps.googleusercontent.com",
              "client_type": 3
            }
          ]
        }
      }
    }
  ],
  "configuration_version": "1"
}